huaweicloudsdkworkspace/__init__.py
huaweicloudsdkworkspace/v2/__init__.py
huaweicloudsdkworkspace/v2/workspace_async_client.py
huaweicloudsdkworkspace/v2/workspace_client.py
huaweicloudsdkworkspace/v2/model/__init__.py
huaweicloudsdkworkspace/v2/model/access_config.py
huaweicloudsdkworkspace/v2/model/access_config_info.py
huaweicloudsdkworkspace/v2/model/access_config_req.py
huaweicloudsdkworkspace/v2/model/access_policy_detail_info.py
huaweicloudsdkworkspace/v2/model/access_policy_info.py
huaweicloudsdkworkspace/v2/model/access_policy_object.py
huaweicloudsdkworkspace/v2/model/access_policy_object_info.py
huaweicloudsdkworkspace/v2/model/account_info.py
huaweicloudsdkworkspace/v2/model/account_type_enum.py
huaweicloudsdkworkspace/v2/model/actions_of_users_in_group_request.py
huaweicloudsdkworkspace/v2/model/ad_domain.py
huaweicloudsdkworkspace/v2/model/ad_domain_info.py
huaweicloudsdkworkspace/v2/model/ad_info.py
huaweicloudsdkworkspace/v2/model/ad_ou_info.py
huaweicloudsdkworkspace/v2/model/ad_ou_user_info.py
huaweicloudsdkworkspace/v2/model/add_desktop_pool_volumes_req.py
huaweicloudsdkworkspace/v2/model/add_desktop_pool_volumes_request.py
huaweicloudsdkworkspace/v2/model/add_desktop_pool_volumes_response.py
huaweicloudsdkworkspace/v2/model/add_desktop_sub_resources_req.py
huaweicloudsdkworkspace/v2/model/add_desktop_sub_resources_request.py
huaweicloudsdkworkspace/v2/model/add_desktop_sub_resources_response.py
huaweicloudsdkworkspace/v2/model/add_desktop_volumes_req.py
huaweicloudsdkworkspace/v2/model/add_desktop_volumes_request.py
huaweicloudsdkworkspace/v2/model/add_desktop_volumes_response.py
huaweicloudsdkworkspace/v2/model/add_desktops_volumes_req.py
huaweicloudsdkworkspace/v2/model/add_metric_notify_rule_req.py
huaweicloudsdkworkspace/v2/model/add_metric_notify_rule_request.py
huaweicloudsdkworkspace/v2/model/add_metric_notify_rule_response.py
huaweicloudsdkworkspace/v2/model/add_ou_name_info_v2_req.py
huaweicloudsdkworkspace/v2/model/add_ou_request.py
huaweicloudsdkworkspace-3.1.184.dist-info/METADATA
huaweicloudsdkworkspace-3.1.184.dist-info/WHEEL
huaweicloudsdkworkspace-3.1.184.dist-info/licenses/LICENSE
huaweicloudsdkworkspace-3.1.184.dist-info/RECORD
